odoo/addons/l10n_ch_delivery_carrier_label_quickpac/README.rst
odoo/addons/l10n_ch_delivery_carrier_label_quickpac/__init__.py
odoo/addons/l10n_ch_delivery_carrier_label_quickpac/__manifest__.py
odoo/addons/l10n_ch_delivery_carrier_label_quickpac/data/delivery.xml
odoo/addons/l10n_ch_delivery_carrier_label_quickpac/data/delivery_option.xml
odoo/addons/l10n_ch_delivery_carrier_label_quickpac/data/delivery_template_option.xml
odoo/addons/l10n_ch_delivery_carrier_label_quickpac/data/partner.xml
odoo/addons/l10n_ch_delivery_carrier_label_quickpac/data/product.xml
odoo/addons/l10n_ch_delivery_carrier_label_quickpac/i18n/l10n_ch_delivery_carrier_label_quickpac.pot
odoo/addons/l10n_ch_delivery_carrier_label_quickpac/models/__init__.py
odoo/addons/l10n_ch_delivery_carrier_label_quickpac/models/company.py
odoo/addons/l10n_ch_delivery_carrier_label_quickpac/models/delivery.py
odoo/addons/l10n_ch_delivery_carrier_label_quickpac/models/res_config_settings.py
odoo/addons/l10n_ch_delivery_carrier_label_quickpac/models/stock.py
odoo/addons/l10n_ch_delivery_carrier_label_quickpac/quickpac/__init__.py
odoo/addons/l10n_ch_delivery_carrier_label_quickpac/quickpac/helpers.py
odoo/addons/l10n_ch_delivery_carrier_label_quickpac/quickpac/web_service.py
odoo/addons/l10n_ch_delivery_carrier_label_quickpac/readme/CONFIGURE.rst
odoo/addons/l10n_ch_delivery_carrier_label_quickpac/readme/CONTRIBUTORS.rst
odoo/addons/l10n_ch_delivery_carrier_label_quickpac/readme/CREDITS.rst
odoo/addons/l10n_ch_delivery_carrier_label_quickpac/readme/DESCRIPTION.rst
odoo/addons/l10n_ch_delivery_carrier_label_quickpac/readme/INSTALL.rst
odoo/addons/l10n_ch_delivery_carrier_label_quickpac/static/description/icon.svg
odoo/addons/l10n_ch_delivery_carrier_label_quickpac/static/description/index.html
odoo/addons/l10n_ch_delivery_carrier_label_quickpac/static/img/quickpac-logo.jpg
odoo/addons/l10n_ch_delivery_carrier_label_quickpac/tests/__init__.py
odoo14_addon_l10n_ch_delivery_carrier_label_quickpac-14.0.1.0.1.dist-info/METADATA
odoo14_addon_l10n_ch_delivery_carrier_label_quickpac-14.0.1.0.1.dist-info/WHEEL
odoo14_addon_l10n_ch_delivery_carrier_label_quickpac-14.0.1.0.1.dist-info/top_level.txt
odoo14_addon_l10n_ch_delivery_carrier_label_quickpac-14.0.1.0.1.dist-info/RECORD
